[
  {
    "mal_id": 2903,
    "url": "https://myanimelist.net/anime/2903/Sakigake_Otokojuku",
    "images": {
      "jpg": {
        "image_url": "https://cdn.myanimelist.net/images/anime/12/60397.jpg",
        "small_image_url": "https://cdn.myanimelist.net/images/anime/12/60397t.jpg",
        "large_image_url": "https://cdn.myanimelist.net/images/anime/12/60397l.jpg"
      },
      "webp": {
        "image_url": "https://cdn.myanimelist.net/images/anime/12/60397.webp",
        "small_image_url": "https://cdn.myanimelist.net/images/anime/12/60397t.webp",
        "large_image_url": "https://cdn.myanimelist.net/images/anime/12/60397l.webp"
      }
    },
    "trailer": {
      "youtube_id": null,
      "url": null,
      "embed_url": null,
      "images": {
        "image_url": null,
        "small_image_url": null,
        "medium_image_url": null,
        "large_image_url": null,
        "maximum_image_url": null
      }
    },
    "approved": true,
    "titles": [
      {
        "type": "Default",
        "title": "Sakigake!! Otokojuku"
      },
      {
        "type": "Synonym",
        "title": "Be A Man! Samurai School"
      },
      {
        "type": "Japanese",
        "title": "\u9b41!!\u7537\u587e"
      },
      {
        "type": "English",
        "title": "Charge!! Men's Private School"
      }
    ],
    "title": "Sakigake!! Otokojuku",
    "title_english": "Charge!! Men's Private School",
    "title_japanese": "\u9b41!!\u7537\u587e",
    "title_synonyms": [
      "Be A Man! Samurai School"
    ],
    "type": "TV",
    "source": "Manga",
    "episodes": 34,
    "status": "Finished Airing",
    "airing": false,
    "aired": {
      "from": "1988-02-25T00:00:00+00:00",
      "to": "1988-11-14T00:00:00+00:00",
      "prop": {
        "from": {
          "day": 25,
          "month": 2,
          "year": 1988
        },
        "to": {
          "day": 14,
          "month": 11,
          "year": 1988
        }
      },
      "string": "Feb 25, 1988 to Nov 14, 1988"
    },
    "duration": "24 min per ep",
    "rating": "R - 17+ (violence & profanity)",
    "score": 7.4,
    "scored_by": 3359,
    "rank": 2071,
    "popularity": 5319,
    "members": 13498,
    "favorites": 102,
    "synopsis": "Otokojuku: a private school for juvenile delinquents that were previously expelled from normal schools. At this school, Japanese chivalry is taught through feudal and military fundamentals. Similar to an action film, the classes are overwhelmed by violence. Only those who survive it become true men.\n\n(Source: ANN)",
    "background": null,
    "season": "winter",
    "year": 1988,
    "broadcast": {
      "day": "Mondays",
      "time": "19:00",
      "timezone": "Asia/Tokyo",
      "string": "Mondays at 19:00 (JST)"
    },
    "producers": [
      {
        "mal_id": 104,
        "type": "anime",
        "name": "Lantis",
        "url": "https://myanimelist.net/anime/producer/104/Lantis"
      }
    ],
    "licensors": [],
    "studios": [
      {
        "mal_id": 18,
        "type": "anime",
        "name": "Toei Animation",
        "url": "https://myanimelist.net/anime/producer/18/Toei_Animation"
      }
    ],
    "genres": [
      {
        "mal_id": 1,
        "type": "anime",
        "name": "Action",
        "url": "https://myanimelist.net/anime/genre/1/Action"
      },
      {
        "mal_id": 4,
        "type": "anime",
        "name": "Comedy",
        "url": "https://myanimelist.net/anime/genre/4/Comedy"
      }
    ],
    "explicit_genres": [],
    "themes": [
      {
        "mal_id": 55,
        "type": "anime",
        "name": "Delinquents",
        "url": "https://myanimelist.net/anime/genre/55/Delinquents"
      },
      {
        "mal_id": 17,
        "type": "anime",
        "name": "Martial Arts",
        "url": "https://myanimelist.net/anime/genre/17/Martial_Arts"
      },
      {
        "mal_id": 23,
        "type": "anime",
        "name": "School",
        "url": "https://myanimelist.net/anime/genre/23/School"
      }
    ],
    "demographics": [
      {
        "mal_id": 27,
        "type": "anime",
        "name": "Shounen",
        "url": "https://myanimelist.net/anime/genre/27/Shounen"
      }
    ]
  },
  {
    "mal_id": 9883,
    "url": "https://myanimelist.net/anime/9883/Osomatsu-kun_1988",
    "images": {
      "jpg": {
        "image_url": "https://cdn.myanimelist.net/images/anime/1991/134376.jpg",
        "small_image_url": "https://cdn.myanimelist.net/images/anime/1991/134376t.jpg",
        "large_image_url": "https://cdn.myanimelist.net/images/anime/1991/134376l.jpg"
      },
      "webp": {
        "image_url": "https://cdn.myanimelist.net/images/anime/1991/134376.webp",
        "small_image_url": "https://cdn.myanimelist.net/images/anime/1991/134376t.webp",
        "large_image_url": "https://cdn.myanimelist.net/images/anime/1991/134376l.webp"
      }
    },
    "trailer": {
      "youtube_id": null,
      "url": null,
      "embed_url": null,
      "images": {
        "image_url": null,
        "small_image_url": null,
        "medium_image_url": null,
        "large_image_url": null,
        "maximum_image_url": null
      }
    },
    "approved": true,
    "titles": [
      {
        "type": "Default",
        "title": "Osomatsu-kun (1988)"
      },
      {
        "type": "Japanese",
        "title": "\u304a\u305d\u677e\u304f\u3093"
      },
      {
        "type": "English",
        "title": "Osomatsu-kun (1988)"
      }
    ],
    "title": "Osomatsu-kun (1988)",
    "title_english": "Osomatsu-kun (1988)",
    "title_japanese": "\u304a\u305d\u677e\u304f\u3093",
    "title_synonyms": [],
    "type": "TV",
    "source": "Manga",
    "episodes": 86,
    "status": "Finished Airing",
    "airing": false,
    "aired": {
      "from": "1988-02-13T00:00:00+00:00",
      "to": "1989-12-30T00:00:00+00:00",
      "prop": {
        "from": {
          "day": 13,
          "month": 2,
          "year": 1988
        },
        "to": {
          "day": 30,
          "month": 12,
          "year": 1989
        }
      },
      "string": "Feb 13, 1988 to Dec 30, 1989"
    },
    "duration": "24 min per ep",
    "rating": "G - All Ages",
    "score": 6.7,
    "scored_by": 1491,
    "rank": 5326,
    "popularity": 7367,
    "members": 6059,
    "favorites": 27,
    "synopsis": "Meet the Osomatsu boys\u2014sextuplets who look, speak, dress and talk like the same. They only add to the hyper eccentric residents of the town who easily break any boundaries defined by common sense. Check your logical thinking and reason at the door and immerse yourself in everyday lives of unique characters who are wild both in appearance and temperament!\n\n(Source: Studio Pierrot)",
    "background": null,
    "season": "winter",
    "year": 1988,
    "broadcast": {
      "day": "Saturdays",
      "time": "18:30",
      "timezone": "Asia/Tokyo",
      "string": "Saturdays at 18:30 (JST)"
    },
    "producers": [
      {
        "mal_id": 169,
        "type": "anime",
        "name": "Fuji TV",
        "url": "https://myanimelist.net/anime/producer/169/Fuji_TV"
      },
      {
        "mal_id": 675,
        "type": "anime",
        "name": "Yomiuri Advertising",
        "url": "https://myanimelist.net/anime/producer/675/Yomiuri_Advertising"
      },
      {
        "mal_id": 769,
        "type": "anime",
        "name": "Fujipacific Music",
        "url": "https://myanimelist.net/anime/producer/769/Fujipacific_Music"
      }
    ],
    "licensors": [
      {
        "mal_id": 467,
        "type": "anime",
        "name": "Discotek Media",
        "url": "https://myanimelist.net/anime/producer/467/Discotek_Media"
      }
    ],
    "studios": [
      {
        "mal_id": 1,
        "type": "anime",
        "name": "Pierrot",
        "url": "https://myanimelist.net/anime/producer/1/Pierrot"
      }
    ],
    "genres": [
      {
        "mal_id": 4,
        "type": "anime",
        "name": "Comedy",
        "url": "https://myanimelist.net/anime/genre/4/Comedy"
      }
    ],
    "explicit_genres": [],
    "themes": [
      {
        "mal_id": 57,
        "type": "anime",
        "name": "Gag Humor",
        "url": "https://myanimelist.net/anime/genre/57/Gag_Humor"
      }
    ],
    "demographics": [
      {
        "mal_id": 27,
        "type": "anime",
        "name": "Shounen",
        "url": "https://myanimelist.net/anime/genre/27/Shounen"
      }
    ]
  },
  {
    "mal_id": 2555,
    "url": "https://myanimelist.net/anime/2555/Shoukoushi_Cedie",
    "images": {
      "jpg": {
        "image_url": "https://cdn.myanimelist.net/images/anime/5/3273.jpg",
        "small_image_url": "https://cdn.myanimelist.net/images/anime/5/3273t.jpg",
        "large_image_url": "https://cdn.myanimelist.net/images/anime/5/3273l.jpg"
      },
      "webp": {
        "image_url": "https://cdn.myanimelist.net/images/anime/5/3273.webp",
        "small_image_url": "https://cdn.myanimelist.net/images/anime/5/3273t.webp",
        "large_image_url": "https://cdn.myanimelist.net/images/anime/5/3273l.webp"
      }
    },
    "trailer": {
      "youtube_id": null,
      "url": null,
      "embed_url": null,
      "images": {
        "image_url": null,
        "small_image_url": null,
        "medium_image_url": null,
        "large_image_url": null,
        "maximum_image_url": null
      }
    },
    "approved": true,
    "titles": [
      {
        "type": "Default",
        "title": "Shoukoushi Cedie"
      },
      {
        "type": "Synonym",
        "title": "Sekai Meisaku Gekijou"
      },
      {
        "type": "Synonym",
        "title": "Little Prince Cedie"
      },
      {
        "type": "Japanese",
        "title": "\u5c0f\u516c\u5b50\u30bb\u30c7\u30a3"
      },
      {
        "type": "English",
        "title": "Little Lord Fauntleroy"
      }
    ],
    "title": "Shoukoushi Cedie",
    "title_english": "Little Lord Fauntleroy",
    "title_japanese": "\u5c0f\u516c\u5b50\u30bb\u30c7\u30a3",
    "title_synonyms": [
      "Sekai Meisaku Gekijou",
      "Little Prince Cedie"
    ],
    "type": "TV",
    "source": "Novel",
    "episodes": 43,
    "status": "Finished Airing",
    "airing": false,
    "aired": {
      "from": "1988-01-10T00:00:00+00:00",
      "to": "1988-12-25T00:00:00+00:00",
      "prop": {
        "from": {
          "day": 10,
          "month": 1,
          "year": 1988
        },
        "to": {
          "day": 25,
          "month": 12,
          "year": 1988
        }
      },
      "string": "Jan 10, 1988 to Dec 25, 1988"
    },
    "duration": "24 min per ep",
    "rating": "G - All Ages",
    "score": 7.31,
    "scored_by": 1440,
    "rank": 2457,
    "popularity": 8423,
    "members": 4312,
    "favorites": 14,
    "synopsis": "After his father's sudden death, Ceddie moves to England as an heir to his grandfather, the Earl of Dorincourt. \n\nThe Earl is a stubborn and selfish old man. Gradually, however, Ceddie's innocent love opens the Earl's heart and changes him into a caring and generous person. \n\nThis is based on \"Little Lord Fauntleroy\" by F.H.Burnett. \n\n(Source: AnimeNfo)",
    "background": null,
    "season": "winter",
    "year": 1988,
    "broadcast": {
      "day": "Sundays",
      "time": "19:30",
      "timezone": "Asia/Tokyo",
      "string": "Sundays at 19:30 (JST)"
    },
    "producers": [
      {
        "mal_id": 169,
        "type": "anime",
        "name": "Fuji TV",
        "url": "https://myanimelist.net/anime/producer/169/Fuji_TV"
      }
    ],
    "licensors": [],
    "studios": [
      {
        "mal_id": 22,
        "type": "anime",
        "name": "Nippon Animation",
        "url": "https://myanimelist.net/anime/producer/22/Nippon_Animation"
      }
    ],
    "genres": [
      {
        "mal_id": 8,
        "type": "anime",
        "name": "Drama",
        "url": "https://myanimelist.net/anime/genre/8/Drama"
      },
      {
        "mal_id": 36,
        "type": "anime",
        "name": "Slice of Life",
        "url": "https://myanimelist.net/anime/genre/36/Slice_of_Life"
      }
    ],
    "explicit_genres": [],
    "themes": [
      {
        "mal_id": 13,
        "type": "anime",
        "name": "Historical",
        "url": "https://myanimelist.net/anime/genre/13/Historical"
      }
    ],
    "demographics": []
  },
  {
    "mal_id": 3259,
    "url": "https://myanimelist.net/anime/3259/Lemon_Angel_1988",
    "images": {
      "jpg": {
        "image_url": "https://cdn.myanimelist.net/images/anime/2/5164.jpg",
        "small_image_url": "https://cdn.myanimelist.net/images/anime/2/5164t.jpg",
        "large_image_url": "https://cdn.myanimelist.net/images/anime/2/5164l.jpg"
      },
      "webp": {
        "image_url": "https://cdn.myanimelist.net/images/anime/2/5164.webp",
        "small_image_url": "https://cdn.myanimelist.net/images/anime/2/5164t.webp",
        "large_image_url": "https://cdn.myanimelist.net/images/anime/2/5164l.webp"
      }
    },
    "trailer": {
      "youtube_id": null,
      "url": null,
      "embed_url": null,
      "images": {
        "image_url": null,
        "small_image_url": null,
        "medium_image_url": null,
        "large_image_url": null,
        "maximum_image_url": null
      }
    },
    "approved": true,
    "titles": [
      {
        "type": "Default",
        "title": "Lemon Angel (1988)"
      },
      {
        "type": "Synonym",
        "title": "Midnight Anime: Lemon Angel"
      },
      {
        "type": "Japanese",
        "title": "\u30ec\u30e2\u30f3\u30a8\u30f3\u30b8\u30a7\u30eb"
      },
      {
        "type": "English",
        "title": "Lemon Angel (1988)"
      }
    ],
    "title": "Lemon Angel (1988)",
    "title_english": "Lemon Angel (1988)",
    "title_japanese": "\u30ec\u30e2\u30f3\u30a8\u30f3\u30b8\u30a7\u30eb",
    "title_synonyms": [
      "Midnight Anime: Lemon Angel"
    ],
    "type": "TV",
    "source": "Unknown",
    "episodes": 9,
    "status": "Finished Airing",
    "airing": false,
    "aired": {
      "from": "1988-02-03T00:00:00+00:00",
      "to": "1988-03-30T00:00:00+00:00",
      "prop": {
        "from": {
          "day": 3,
          "month": 2,
          "year": 1988
        },
        "to": {
          "day": 30,
          "month": 3,
          "year": 1988
        }
      },
      "string": "Feb 3, 1988 to Mar 30, 1988"
    },
    "duration": "3 min per ep",
    "rating": "R+ - Mild Nudity",
    "score": 5.7,
    "scored_by": 423,
    "rank": 10025,
    "popularity": 10763,
    "members": 1908,
    "favorites": 1,
    "synopsis": "The sequel of the Cream Lemon: Lemon Angel.",
    "background": null,
    "season": "winter",
    "year": 1988,
    "broadcast": {
      "day": null,
      "time": null,
      "timezone": null,
      "string": "Unknown"
    },
    "producers": [
      {
        "mal_id": 144,
        "type": "anime",
        "name": "Pony Canyon",
        "url": "https://myanimelist.net/anime/producer/144/Pony_Canyon"
      }
    ],
    "licensors": [],
    "studios": [
      {
        "mal_id": 48,
        "type": "anime",
        "name": "AIC",
        "url": "https://myanimelist.net/anime/producer/48/AIC"
      }
    ],
    "genres": [
      {
        "mal_id": 9,
        "type": "anime",
        "name": "Ecchi",
        "url": "https://myanimelist.net/anime/genre/9/Ecchi"
      }
    ],
    "explicit_genres": [],
    "themes": [],
    "demographics": []
  },
  {
    "mal_id": 4427,
    "url": "https://myanimelist.net/anime/4427/Tatakae_Ramenman",
    "images": {
      "jpg": {
        "image_url": "https://cdn.myanimelist.net/images/anime/7/8414.jpg",
        "small_image_url": "https://cdn.myanimelist.net/images/anime/7/8414t.jpg",
        "large_image_url": "https://cdn.myanimelist.net/images/anime/7/8414l.jpg"
      },
      "webp": {
        "image_url": "https://cdn.myanimelist.net/images/anime/7/8414.webp",
        "small_image_url": "https://cdn.myanimelist.net/images/anime/7/8414t.webp",
        "large_image_url": "https://cdn.myanimelist.net/images/anime/7/8414l.webp"
      }
    },
    "trailer": {
      "youtube_id": null,
      "url": null,
      "embed_url": null,
      "images": {
        "image_url": null,
        "small_image_url": null,
        "medium_image_url": null,
        "large_image_url": null,
        "maximum_image_url": null
      }
    },
    "approved": true,
    "titles": [
      {
        "type": "Default",
        "title": "Tatakae!! Ramenman"
      },
      {
        "type": "Synonym",
        "title": "Toushou!! Ramenman"
      },
      {
        "type": "Japanese",
        "title": "\u95d8\u5c06!!\u62c9\u9eba\u7537"
      },
      {
        "type": "English",
        "title": "Fight!! Ramenman"
      }
    ],
    "title": "Tatakae!! Ramenman",
    "title_english": "Fight!! Ramenman",
    "title_japanese": "\u95d8\u5c06!!\u62c9\u9eba\u7537",
    "title_synonyms": [
      "Toushou!! Ramenman"
    ],
    "type": "TV",
    "source": "Unknown",
    "episodes": 35,
    "status": "Finished Airing",
    "airing": false,
    "aired": {
      "from": "1988-01-10T00:00:00+00:00",
      "to": "1988-09-11T00:00:00+00:00",
      "prop": {
        "from": {
          "day": 10,
          "month": 1,
          "year": 1988
        },
        "to": {
          "day": 11,
          "month": 9,
          "year": 1988
        }
      },
      "string": "Jan 10, 1988 to Sep 11, 1988"
    },
    "duration": "23 min per ep",
    "rating": "R - 17+ (violence & profanity)",
    "score": 6.28,
    "scored_by": 325,
    "rank": 7470,
    "popularity": 11442,
    "members": 1481,
    "favorites": 9,
    "synopsis": "Set in a land where several martial arts styles collide, including (but not limited to) Chinese Kung Fu, Japanese Karate, and South Korean Taekwondo. Yet amongst these Shaolin-trained fighters and men powerful enough to cut the face of a mountain, Victory Ramenman is said to be the strongest of them all. At a young age, he witnessed his father Somenman being murdered by members of the Cobra Gang (who are still running rampant to this day). Found and taken in by the wise old Chen Sou-Mei, Ramenman trains for 12 years under his master and learns the great Essential Battle Dragon (\u95d8\u9f8d\u6975\u610f\u66f8, To Ryuu Gokui Sho) style of Choujin Martial arts. Now, with his young sidekick Shao-Mai, Ramenman travels the land seeking vengeance for his father, fighting several villains along the way.\n\n(Source: Wikipedia)",
    "background": null,
    "season": "winter",
    "year": 1988,
    "broadcast": {
      "day": null,
      "time": null,
      "timezone": null,
      "string": "Unknown"
    },
    "producers": [
      {
        "mal_id": 127,
        "type": "anime",
        "name": "Yomiko Advertising",
        "url": "https://myanimelist.net/anime/producer/127/Yomiko_Advertising"
      }
    ],
    "licensors": [],
    "studios": [
      {
        "mal_id": 18,
        "type": "anime",
        "name": "Toei Animation",
        "url": "https://myanimelist.net/anime/producer/18/Toei_Animation"
      }
    ],
    "genres": [
      {
        "mal_id": 1,
        "type": "anime",
        "name": "Action",
        "url": "https://myanimelist.net/anime/genre/1/Action"
      },
      {
        "mal_id": 2,
        "type": "anime",
        "name": "Adventure",
        "url": "https://myanimelist.net/anime/genre/2/Adventure"
      }
    ],
    "explicit_genres": [],
    "themes": [
      {
        "mal_id": 17,
        "type": "anime",
        "name": "Martial Arts",
        "url": "https://myanimelist.net/anime/genre/17/Martial_Arts"
      }
    ],
    "demographics": [
      {
        "mal_id": 27,
        "type": "anime",
        "name": "Shounen",
        "url": "https://myanimelist.net/anime/genre/27/Shounen"
      }
    ]
  },
  {
    "mal_id": 8158,
    "url": "https://myanimelist.net/anime/8158/Gegege_no_Kitarou__Jigoku-hen",
    "images": {
      "jpg": {
        "image_url": "https://cdn.myanimelist.net/images/anime/6/90097.jpg",
        "small_image_url": "https://cdn.myanimelist.net/images/anime/6/90097t.jpg",
        "large_image_url": "https://cdn.myanimelist.net/images/anime/6/90097l.jpg"
      },
      "webp": {
        "image_url": "https://cdn.myanimelist.net/images/anime/6/90097.webp",
        "small_image_url": "https://cdn.myanimelist.net/images/anime/6/90097t.webp",
        "large_image_url": "https://cdn.myanimelist.net/images/anime/6/90097l.webp"
      }
    },
    "trailer": {
      "youtube_id": null,
      "url": null,
      "embed_url": null,
      "images": {
        "image_url": null,
        "small_image_url": null,
        "medium_image_url": null,
        "large_image_url": null,
        "maximum_image_url": null
      }
    },
    "approved": true,
    "titles": [
      {
        "type": "Default",
        "title": "Gegege no Kitarou: Jigoku-hen"
      },
      {
        "type": "Synonym",
        "title": "Gegege no Kitarou: Jigokuhen"
      },
      {
        "type": "Synonym",
        "title": "Gegege no Kitarou: Jigoku Hen"
      },
      {
        "type": "Japanese",
        "title": "\u30b2\u30b2\u30b2\u306e\u9b3c\u592a\u90ce\u3000\u5730\u7344\u7de8"
      }
    ],
    "title": "Gegege no Kitarou: Jigoku-hen",
    "title_english": null,
    "title_japanese": "\u30b2\u30b2\u30b2\u306e\u9b3c\u592a\u90ce\u3000\u5730\u7344\u7de8",
    "title_synonyms": [
      "Gegege no Kitarou: Jigokuhen",
      "Gegege no Kitarou: Jigoku Hen"
    ],
    "type": "TV",
    "source": "Unknown",
    "episodes": 7,
    "status": "Finished Airing",
    "airing": false,
    "aired": {
      "from": "1988-02-08T00:00:00+00:00",
      "to": "1988-03-21T00:00:00+00:00",
      "prop": {
        "from": {
          "day": 8,
          "month": 2,
          "year": 1988
        },
        "to": {
          "day": 21,
          "month": 3,
          "year": 1988
        }
      },
      "string": "Feb 8, 1988 to Mar 21, 1988"
    },
    "duration": "25 min per ep",
    "rating": "G - All Ages",
    "score": 6.09,
    "scored_by": 244,
    "rank": 8392,
    "popularity": 12287,
    "members": 1101,
    "favorites": 0,
    "synopsis": "The origins of Kitarou.",
    "background": null,
    "season": "winter",
    "year": 1988,
    "broadcast": {
      "day": null,
      "time": null,
      "timezone": null,
      "string": "Unknown"
    },
    "producers": [],
    "licensors": [],
    "studios": [
      {
        "mal_id": 18,
        "type": "anime",
        "name": "Toei Animation",
        "url": "https://myanimelist.net/anime/producer/18/Toei_Animation"
      }
    ],
    "genres": [
      {
        "mal_id": 2,
        "type": "anime",
        "name": "Adventure",
        "url": "https://myanimelist.net/anime/genre/2/Adventure"
      },
      {
        "mal_id": 4,
        "type": "anime",
        "name": "Comedy",
        "url": "https://myanimelist.net/anime/genre/4/Comedy"
      },
      {
        "mal_id": 10,
        "type": "anime",
        "name": "Fantasy",
        "url": "https://myanimelist.net/anime/genre/10/Fantasy"
      },
      {
        "mal_id": 14,
        "type": "anime",
        "name": "Horror",
        "url": "https://myanimelist.net/anime/genre/14/Horror"
      },
      {
        "mal_id": 37,
        "type": "anime",
        "name": "Supernatural",
        "url": "https://myanimelist.net/anime/genre/37/Supernatural"
      }
    ],
    "explicit_genres": [],
    "themes": [],
    "demographics": []
  }
]